{
    "PressAnyKeyToExit": "Apasă pe orice tastă pentru a ieși",
    "ExceptionCaught": "A APĂRUT O EROARE!",
    "AssemblyMissing": "Could not find the assembly file.\nPlease make sure you have installed QModManager in the right folder.",
    "ExecutableMissing": "Could not find any game to patch!\nAn assembly file was found, but no executable was detected.\nPlease make sure you have installed QModManager in the right folder.",
    "Installing": "Se instalează QModManager...",
    "Uninstalling": "Se dezinstalează QModManager...",
    "AlreadyUninstalled": "QModManager nu este instalat!",
    "AskInstall": "No patch detected, install?",
    "AskUninstall": "Patch installed, remove?",
    "Dialog_SeeLog": "Consolă",
    "Dialog_Close": "Închide",
    "AlreadyInstalled_Forced": "Tried to install, but it was already injected\nSkipping installation",
    "Installed": "QModManager a fost instalat cu succes",
    "AlreadyUninstalled_Forced": "Tried to uninstall, but patch was not present\nSkipping uninstallation",
    "Uninstalled": "QModManager a fost dezinstalat cu succes",
    "CalledMultipleTimes": "Patch method was called multiple times!",
    "LoadedMods": "Mod-uri încărcate:",
    "ErroredMods": "Următoarele moduri nu au putut fi încărcate:",
    "EntryMethodMissing": "Niciun punct de intrare (EntryMethod) definit pentru mod-ul '{0}'",
    "EntryMethodUnparseable": "Nu s-a putut găsi punctul de intrare (EntryMethod) '{0}' pentru mod-ul '{1}'",
    "EntryMethodInvokeFailed": "Nu s-a putut rula punctul de intrare (EntryMethod) '{0}' pentru mod-ul '{1}'",
    "UnexpectedError": "A apărut o eroare neașteptată in timpul încărcării mod-ului '{0}'",
    "SortingLoopError": "A apărut o eroare în timpul sortării următoarelor mod-uri!\nVerificați setările încarcă după (LoadAfter) și încarcă înainte (LoadBefore) pentru urmatoarele moduri:",
    "MissingDependencies": "Următoarele mod-uri nu au putut fi încărcate datorită dependențelor lipsă:",
    "MissingDependenciesMod": "(lipsă: {0})",
    "Dialog_ErroredMods": "Următoarele moduri nu au putut fi încărcate:",
    "CheckTheLog": "Verifică consola pentru detalii.",
    "Dialog_NewVersionAvailable": "Există o versiune mai nouă QModManager: {0} (versiune actuală: {1})",
    "DeserializationFailed": "Nu s-a putut incărca fișierul mod.json pentru mod-ul: {0}",
    "VersionCheckError": "Nu s-a putut obține cea mai recentă versiune! ({0})",
    "LoadLanguage": "Se incarcă limba {0}...",
    "AlreadyInstalled": "QModManager este deja instalat!",
    "Yes": "Da",
    "No": "Nu",
    "IfTheProblemPersists": "Dacă problema persistă, raportează un bug pe pagina de NexusMods sau deschide un issue pe pagina de GitHub"
}